{
    "resolvers": {
        "Mutation.initStripeCustomer": {
            "noCode": {
                "package": "gei-stripe",
                "version": "0.2.0",
                "resolver": "initStripeCustomer"
            },
            "resolve": {
                "name": "gei-stripe@Mutation.initStripeCustomer"
            }
        },
        "Mutation.createNewUserCheckoutSession": {
            "noCode": {
                "package": "gei-stripe",
                "version": "0.2.0",
                "resolver": "createNewUserCheckoutSession"
            },
            "resolve": {
                "name": "gei-stripe@Mutation.createNewUserCheckoutSession"
            }
        },
        "Mutation.createCheckoutSession": {
            "noCode": {
                "package": "gei-stripe",
                "version": "0.2.0",
                "resolver": "createCheckoutSession"
            },
            "resolve": {
                "name": "gei-stripe@Mutation.createCheckoutSession"
            }
        },
        "Mutation.webhook": {
            "noCode": {
                "package": "gei-stripe",
                "version": "0.2.0",
                "resolver": "webhook"
            },
            "resolve": {
                "name": "gei-stripe@Mutation.webhook"
            }
        },
        "Query.products": {
            "noCode": {
                "package": "gei-stripe",
                "version": "0.2.0",
                "resolver": "products"
            },
            "resolve": {
                "name": "gei-stripe@Query.products"
            }
        },
        "Query.subscriptions": {
            "noCode": {
                "package": "gei-stripe",
                "version": "0.2.0",
                "resolver": "products"
            },
            "resolve": {
                "name": "gei-stripe@Query.subscriptions"
            }
        },
        "Product.default_price": {
            "noCode": {
                "package": "gei-stripe",
                "version": "0.2.0",
                "resolver": "default_price"
            },
            "resolve": {
                "name": "gei-stripe@Product.default_price"
            }
        },
        "Product.prices": {
            "noCode": {
                "package": "gei-stripe",
                "version": "0.2.0",
                "resolver": "prices"
            },
            "resolve": {
                "name": "gei-stripe@Product.prices"
            }
        }
    },
    "azureOpts": {
        "webhooks": [
            "webhook/Mutation/webhook"
        ]
    }
}